geyser_lava/__init__.py
geyser_lava/profile/__init__.py
geyser_lava/profile/_support/__init__.py
geyser_lava/profile/_support/operator.py
geyser_lava/profile/hello/hello.hocon
geyser_lava/profile/hello/hello.json
geyser_lava/profile/hello/hello.plist
geyser_lava/profile/hello/hello.toml
geyser_lava/profile/hello/hello.yaml
geyser_lava/profile/torch/train_resnet_cifar10.hocon
geyser_lava/profile/torch/train_resnet_cifar10.json
geyser_lava/profile/torch/train_resnet_cifar10.plist
geyser_lava/profile/torch/train_resnet_cifar10.toml
geyser_lava/profile/torch/train_resnet_cifar10.yaml
geyser_lava/task/__init__.py
geyser_lava/task/hello.py
geyser_lava/task/utility.py
geyser_lava/task/torch/__init__.py
geyser_lava/task/torch/common.py
geyser_lava/task/torch/trainer.py
geyser_lava/utility/__init__.py
geyser_lava/utility/operator.py
geyser_lava-0.1.3.dist-info/LICENSE
geyser_lava-0.1.3.dist-info/METADATA
geyser_lava-0.1.3.dist-info/WHEEL
geyser_lava-0.1.3.dist-info/entry_points.txt
geyser_lava-0.1.3.dist-info/top_level.txt
geyser_lava-0.1.3.dist-info/RECORD
